{"clock": {"increment": 2, "initial": 180, "totalTime": 260}, "createdAt": "2023-10-20 10:14:16.181000+00:00", "id": "517Lsrmb", "lastMoveAt": "2023-10-20 10:18:30.059000+00:00", "moves": "d4 Nf6 Bg5 h6 Bxf6 exf6 c4 Bb4+ Nc3 d5 e3 O-O Qc2 Re8 Nf3 Nc6 a3 Bxc3+ Qxc3 f5 g3 dxc4 Qxc4 Be6 Qc2 Bd5 Bg2 Bxf3 Bxf3 Nxd4", "perf": "blitz", "pgn": "[Event \"Rated blitz game\"]\n[Site \"https://lichess.org/517Lsrmb\"]\n[Date \"2023.10.20\"]\n[White \"Matei_Popescu1510\"]\n[Black \"raf108\"]\n[Result \"0-1\"]\n[UTCDate \"2023.10.20\"]\n[UTCTime \"10:14:16\"]\n[WhiteElo \"1911\"]\n[BlackElo \"1807\"]\n[WhiteRatingDiff \"-7\"]\n[BlackRatingDiff \"+7\"]\n[Variant \"Standard\"]\n[TimeControl \"180+2\"]\n[ECO \"A45\"]\n[Termination \"Normal\"]\n\n1. d4 Nf6 2. Bg5 h6 3. Bxf6 exf6 4. c4 Bb4+ 5. Nc3 d5 6. e3 O-O 7. Qc2 Re8 8. Nf3 Nc6 9. a3 Bxc3+ 10. Qxc3 f5 11. g3 dxc4 12. Qxc4 Be6 13. Qc2 Bd5 14. Bg2 Bxf3 15. Bxf3 Nxd4 0-1\n\n\n", "players": {"black": {"rating": 1807, "ratingDiff": 7, "user": {"id": "raf108", "name": "raf108"}}, "white": {"rating": 1911, "ratingDiff": -7, "user": {"id": "matei_popescu1510", "name": "Matei_Popescu1510"}}}, "rated": true, "source": "pool", "speed": "blitz", "status": "resign", "variant": "standard", "winner": "black"}