{"clock": {"increment": 2, "initial": 180, "totalTime": 260}, "createdAt": "2023-02-07 16:54:16.363000+00:00", "id": "5ccNVjYY", "lastMoveAt": "2023-02-07 17:04:30.790000+00:00", "moves": "d4 d5 e3 c6 Bd3 Nf6 Nd2 Bg4 f3 Bh5 Ne2 Bg6 e4 dxe4 fxe4 e6 c3 Be7 Nf4 Qc7 O-O Nbd7 Nf3 Bxe4 Qe2 Bxd3 Nxd3 O-O Nfe5 Nxe5 Nxe5 Bd6 Bf4 Nd5 Bg3 Nf6 Rae1 Rae8 Qd3 Nd7 Qf3 Nxe5 Bxe5 Bxe5 Rxe5 Qb6 Qe2 Rd8 Kh1 Rd5 Rf2 Rxe5 Qxe5 Rd8 Qf4 Rd7 Rf3 h6 Rf2 Qd8 h3 Qg5 Qxg5 hxg5 Re2 Kh7 Kh2 Kg6 Kg3 Rd5 Kf3 a5 a4 b5 axb5 Rxb5 g4 Kf6 Ke4 Ke7 Kd3 g6 Kc4 f5 b3 Kf6 Ra2 e5 b4 axb4 cxb4 exd4 Kxd4 Rxb4+ Kc5 Rb5+ Kxc6 Rb4 Rg2 fxg4 hxg4 Ke5 Kc5 Rf4 Re2+ Kf6 Rg2 Kg7 Kd5 Kf6 Kc5 Ke5 Re2+ Re4 Rg2 Kf4 Kd5 Ra4 Rg1 Kf3 Ke5 Rxg4 Rf1+ Ke2 Rf7 Rg1 Kf6 g4 Kxg6 g3 Kf6 Rf1+", "perf": "blitz", "pgn": "[Event \"Rated blitz game\"]\n[Site \"https://lichess.org/5ccNVjYY\"]\n[Date \"2023.02.07\"]\n[White \"Matei_Popescu1510\"]\n[Black \"Distributor\"]\n[Result \"0-1\"]\n[UTCDate \"2023.02.07\"]\n[UTCTime \"16:54:16\"]\n[WhiteElo \"1911\"]\n[BlackElo \"1875\"]\n[WhiteRatingDiff \"-6\"]\n[BlackRatingDiff \"+6\"]\n[Variant \"Standard\"]\n[TimeControl \"180+2\"]\n[ECO \"D00\"]\n[Termination \"Normal\"]\n\n1. d4 d5 2. e3 c6 3. Bd3 Nf6 4. Nd2 Bg4 5. f3 Bh5 6. Ne2 Bg6 7. e4 dxe4 8. fxe4 e6 9. c3 Be7 10. Nf4 Qc7 11. O-O Nbd7 12. Nf3 Bxe4 13. Qe2 Bxd3 14. Nxd3 O-O 15. Nfe5 Nxe5 16. Nxe5 Bd6 17. Bf4 Nd5 18. Bg3 Nf6 19. Rae1 Rae8 20. Qd3 Nd7 21. Qf3 Nxe5 22. Bxe5 Bxe5 23. Rxe5 Qb6 24. Qe2 Rd8 25. Kh1 Rd5 26. Rf2 Rxe5 27. Qxe5 Rd8 28. Qf4 Rd7 29. Rf3 h6 30. Rf2 Qd8 31. h3 Qg5 32. Qxg5 hxg5 33. Re2 Kh7 34. Kh2 Kg6 35. Kg3 Rd5 36. Kf3 a5 37. a4 b5 38. axb5 Rxb5 39. g4 Kf6 40. Ke4 Ke7 41. Kd3 g6 42. Kc4 f5 43. b3 Kf6 44. Ra2 e5 45. b4 axb4 46. cxb4 exd4 47. Kxd4 Rxb4+ 48. Kc5 Rb5+ 49. Kxc6 Rb4 50. Rg2 fxg4 51. hxg4 Ke5 52. Kc5 Rf4 53. Re2+ Kf6 54. Rg2 Kg7 55. Kd5 Kf6 56. Kc5 Ke5 57. Re2+ Re4 58. Rg2 Kf4 59. Kd5 Ra4 60. Rg1 Kf3 61. Ke5 Rxg4 62. Rf1+ Ke2 63. Rf7 Rg1 64. Kf6 g4 65. Kxg6 g3 66. Kf6 Rf1+ 0-1\n\n\n", "players": {"black": {"rating": 1875, "ratingDiff": 6, "user": {"flair": "travel-places.compass", "id": "distributor", "name": "Distributor"}}, "white": {"rating": 1911, "ratingDiff": -6, "user": {"id": "matei_popescu1510", "name": "Matei_Popescu1510"}}}, "rated": true, "source": "pool", "speed": "blitz", "status": "resign", "variant": "standard", "winner": "black"}