{"clock": {"increment": 1, "initial": 120, "totalTime": 160}, "createdAt": "2024-04-22 16:19:24.444000+00:00", "id": "7vng93Hb", "lastMoveAt": "2024-04-22 16:26:26.796000+00:00", "moves": "Nf3 Nf6 e3 g6 d4 Bg7 Be2 O-O O-O d6 Nbd2 Nc6 c4 e5 a3 a5 d5 Ne7 e4 Nh5 Re1 f5 Bd3 f4 Qc2 a4 b4 axb3 Qxb3 b6 a4 h6 a5 Rxa5 Rxa5 bxa5 Qa4 g5 Qxa5 Ng6 Bb2 g4 c5 gxf3 Nxf3 Nf6 Ba3 Re8 Bb5 Bd7 c6 Bg4 Be2 Qa8 Bb4 Qxa5 Bxa5 Rc8 Nd2 Bxe2 Rxe2 Ne8 Nc4 Rb8 Rb2 Rxb2 Nxb2 Bf8 f3 Be7 Nc4 Bd8 Be1 Kf7 Na5 Bh4 g3 fxg3 hxg3 Bg5 Kf2 h5 Nb7 Ke7 Ba5 h4 Kg2 hxg3 Kxg3 Bf4+ Kg2 Nh4+ Kf2 Ng6 Bb4 Kf7 Na5 Bg5 Nc4 Nf4 Ba5 Nd3+ Ke2 Nc5 Na3 Kg6 Nb5 Bd8 Ke3 Kg5 Bd2 Nb3 Be1 Nc1 Bd2 Nb3 Be1 Nc5 Kf2 Kg6 Kg3 Nd3 Bc3 Nf4 Bd2 Kg5 Nc3 Nf6 Nb5 Nh5+ Kf2 Kh4 Ke3 Kg3 Be1+ Kg2 Nc3 Ng3 Bxg3 Kxg3 Nb5 Kg2 Nc3 Kg3 Nb5 Ng2+ Ke2 Kf4 Nc3 Nh4 Nd1 Nxf3 Nf2 Kg3 Nd3 Nd4+ Ke3 Bg5+ Nf4 Bxf4+ Kd3 Nf3 Kc4 Be3 Kb5 Bb6 Ka6 Nd2 Kb5 Nxe4 Kc4 Nc5 Kb5 Kf4 Kc4 e4 Kd4 e3 Kc3 Kf3", "perf": "bullet", "pgn": "[Event \"Rated bullet game\"]\n[Site \"https://lichess.org/7vng93Hb\"]\n[Date \"2024.04.22\"]\n[White \"Akh101\"]\n[Black \"Matei_Popescu1510\"]\n[Result \"0-1\"]\n[UTCDate \"2024.04.22\"]\n[UTCTime \"16:19:24\"]\n[WhiteElo \"1709\"]\n[BlackElo \"1768\"]\n[WhiteRatingDiff \"-4\"]\n[BlackRatingDiff \"+22\"]\n[Variant \"Standard\"]\n[TimeControl \"120+1\"]\n[ECO \"A05\"]\n[Termination \"Time forfeit\"]\n\n1. Nf3 Nf6 2. e3 g6 3. d4 Bg7 4. Be2 O-O 5. O-O d6 6. Nbd2 Nc6 7. c4 e5 8. a3 a5 9. d5 Ne7 10. e4 Nh5 11. Re1 f5 12. Bd3 f4 13. Qc2 a4 14. b4 axb3 15. Qxb3 b6 16. a4 h6 17. a5 Rxa5 18. Rxa5 bxa5 19. Qa4 g5 20. Qxa5 Ng6 21. Bb2 g4 22. c5 gxf3 23. Nxf3 Nf6 24. Ba3 Re8 25. Bb5 Bd7 26. c6 Bg4 27. Be2 Qa8 28. Bb4 Qxa5 29. Bxa5 Rc8 30. Nd2 Bxe2 31. Rxe2 Ne8 32. Nc4 Rb8 33. Rb2 Rxb2 34. Nxb2 Bf8 35. f3 Be7 36. Nc4 Bd8 37. Be1 Kf7 38. Na5 Bh4 39. g3 fxg3 40. hxg3 Bg5 41. Kf2 h5 42. Nb7 Ke7 43. Ba5 h4 44. Kg2 hxg3 45. Kxg3 Bf4+ 46. Kg2 Nh4+ 47. Kf2 Ng6 48. Bb4 Kf7 49. Na5 Bg5 50. Nc4 Nf4 51. Ba5 Nd3+ 52. Ke2 Nc5 53. Na3 Kg6 54. Nb5 Bd8 55. Ke3 Kg5 56. Bd2 Nb3 57. Be1 Nc1 58. Bd2 Nb3 59. Be1 Nc5 60. Kf2 Kg6 61. Kg3 Nd3 62. Bc3 Nf4 63. Bd2 Kg5 64. Nc3 Nf6 65. Nb5 Nh5+ 66. Kf2 Kh4 67. Ke3 Kg3 68. Be1+ Kg2 69. Nc3 Ng3 70. Bxg3 Kxg3 71. Nb5 Kg2 72. Nc3 Kg3 73. Nb5 Ng2+ 74. Ke2 Kf4 75. Nc3 Nh4 76. Nd1 Nxf3 77. Nf2 Kg3 78. Nd3 Nd4+ 79. Ke3 Bg5+ 80. Nf4 Bxf4+ 81. Kd3 Nf3 82. Kc4 Be3 83. Kb5 Bb6 84. Ka6 Nd2 85. Kb5 Nxe4 86. Kc4 Nc5 87. Kb5 Kf4 88. Kc4 e4 89. Kd4 e3 90. Kc3 Kf3 0-1\n\n\n", "players": {"black": {"rating": 1768, "ratingDiff": 22, "user": {"id": "matei_popescu1510", "name": "Matei_Popescu1510"}}, "white": {"rating": 1709, "ratingDiff": -4, "user": {"id": "akh101", "name": "Akh101"}}}, "rated": true, "source": "pool", "speed": "bullet", "status": "outoftime", "variant": "standard", "winner": "black"}