{"clock": {"increment": 2, "initial": 180, "totalTime": 260}, "createdAt": "2022-09-04 13:07:14.894000+00:00", "id": "aIGBTjEe", "lastMoveAt": "2022-09-04 13:14:38.494000+00:00", "moves": "d4 d5 e3 Nf6 Bd3 c5 c3 Nc6 f4 Qb6 Nd2 Bg4 Ngf3 e6 O-O Bd6 Qe1 O-O Ne5 Bf5 Be2 Bxe5 fxe5 Ne4 Bf3 cxd4 exd4 Nxd2 Bxd2 Qxb2 Qe3 Na5 Be2 Rac8 h4 Nc4 Bxc4 Rxc4 g4 Be4 g5 Qc2 h5 Qd3 Qf4 Qh3 Qh2 Qg4+ Kf2 Rfc8 Rg1 Qf3+ Ke1 Rxc3 Bxc3 Rxc3 g6 Re3+ Kd2 Rd3+ Ke1 Qe3+ Kf1 fxg6 hxg6 hxg6 Qc2 Qh3+ Rg2 Rf3+", "perf": "blitz", "pgn": "[Event \"Rated blitz game\"]\n[Site \"https://lichess.org/aIGBTjEe\"]\n[Date \"2022.09.04\"]\n[White \"Matei_Popescu1510\"]\n[Black \"omis777\"]\n[Result \"0-1\"]\n[UTCDate \"2022.09.04\"]\n[UTCTime \"13:07:14\"]\n[WhiteElo \"1936\"]\n[BlackElo \"1941\"]\n[WhiteRatingDiff \"-6\"]\n[BlackRatingDiff \"+8\"]\n[Variant \"Standard\"]\n[TimeControl \"180+2\"]\n[ECO \"D00\"]\n[Termination \"Time forfeit\"]\n\n1. d4 d5 2. e3 Nf6 3. Bd3 c5 4. c3 Nc6 5. f4 Qb6 6. Nd2 Bg4 7. Ngf3 e6 8. O-O Bd6 9. Qe1 O-O 10. Ne5 Bf5 11. Be2 Bxe5 12. fxe5 Ne4 13. Bf3 cxd4 14. exd4 Nxd2 15. Bxd2 Qxb2 16. Qe3 Na5 17. Be2 Rac8 18. h4 Nc4 19. Bxc4 Rxc4 20. g4 Be4 21. g5 Qc2 22. h5 Qd3 23. Qf4 Qh3 24. Qh2 Qg4+ 25. Kf2 Rfc8 26. Rg1 Qf3+ 27. Ke1 Rxc3 28. Bxc3 Rxc3 29. g6 Re3+ 30. Kd2 Rd3+ 31. Ke1 Qe3+ 32. Kf1 fxg6 33. hxg6 hxg6 34. Qc2 Qh3+ 35. Rg2 Rf3+ 0-1\n\n\n", "players": {"black": {"rating": 1941, "ratingDiff": 8, "user": {"id": "omis777", "name": "omis777"}}, "white": {"rating": 1936, "ratingDiff": -6, "user": {"id": "matei_popescu1510", "name": "Matei_Popescu1510"}}}, "rated": true, "source": "pool", "speed": "blitz", "status": "timeout", "variant": "standard", "winner": "black"}