{"clock": {"increment": 2, "initial": 180, "totalTime": 260}, "createdAt": "2022-06-28 16:51:45.674000+00:00", "id": "Bmjc6mRs", "lastMoveAt": "2022-06-28 16:59:31.711000+00:00", "moves": "e4 e6 d4 d5 exd5 exd5 Nf3 Nc6 c4 Bb4+ Nc3 Nge7 Be2 O-O O-O Bg4 Be3 Bxc3 bxc3 Ng6 h3 Be6 cxd5 Bxd5 c4 Bxf3 Bxf3 Qd7 d5 Nce5 Be4 Rae8 Bxg6 Nxg6 Bc5 Ne7 Re1 b6 Bb4 f6 Qd2 Rf7 Re3 Nf5 Rxe8+ Qxe8 Re1 Qd7 Bc3 a5 Qf4 Nd6 Re6 Re7 Rxe7 Qxe7 f3 Qe2 c5 Qc4 Qxc4 Nxc4 cxb6 cxb6 Bd4 Kf7 d6 Ke8 Kf2 Kd7 Kg3 Kxd6 Kf4 Ke6 Ke4 Nd2+ Ke3 Nc4+ Ke4 Nd2+ Ke3 Nc4+ Ke4", "perf": "blitz", "pgn": "[Event \"Rated blitz game\"]\n[Site \"https://lichess.org/Bmjc6mRs\"]\n[Date \"2022.06.28\"]\n[White \"Geevos\"]\n[Black \"Matei_Popescu1510\"]\n[Result \"1/2-1/2\"]\n[UTCDate \"2022.06.28\"]\n[UTCTime \"16:51:45\"]\n[WhiteElo \"1884\"]\n[BlackElo \"1936\"]\n[WhiteRatingDiff \"+1\"]\n[BlackRatingDiff \"-1\"]\n[Variant \"Standard\"]\n[TimeControl \"180+2\"]\n[ECO \"C01\"]\n[Termination \"Normal\"]\n\n1. e4 e6 2. d4 d5 3. exd5 exd5 4. Nf3 Nc6 5. c4 Bb4+ 6. Nc3 Nge7 7. Be2 O-O 8. O-O Bg4 9. Be3 Bxc3 10. bxc3 Ng6 11. h3 Be6 12. cxd5 Bxd5 13. c4 Bxf3 14. Bxf3 Qd7 15. d5 Nce5 16. Be4 Rae8 17. Bxg6 Nxg6 18. Bc5 Ne7 19. Re1 b6 20. Bb4 f6 21. Qd2 Rf7 22. Re3 Nf5 23. Rxe8+ Qxe8 24. Re1 Qd7 25. Bc3 a5 26. Qf4 Nd6 27. Re6 Re7 28. Rxe7 Qxe7 29. f3 Qe2 30. c5 Qc4 31. Qxc4 Nxc4 32. cxb6 cxb6 33. Bd4 Kf7 34. d6 Ke8 35. Kf2 Kd7 36. Kg3 Kxd6 37. Kf4 Ke6 38. Ke4 Nd2+ 39. Ke3 Nc4+ 40. Ke4 Nd2+ 41. Ke3 Nc4+ 42. Ke4 1/2-1/2\n\n\n", "players": {"black": {"rating": 1936, "ratingDiff": -1, "user": {"id": "matei_popescu1510", "name": "Matei_Popescu1510"}}, "white": {"rating": 1884, "ratingDiff": 1, "user": {"id": "geevos", "name": "Geevos"}}}, "rated": true, "source": "pool", "speed": "blitz", "status": "draw", "variant": "standard"}