{"clock": {"increment": 3, "initial": 300, "totalTime": 420}, "createdAt": "2021-07-04 11:50:25.188000+00:00", "id": "D2HbJNUJ", "lastMoveAt": "2021-07-04 11:59:40.961000+00:00", "moves": "e4 c6 d4 d5 e5 c5 c3 Nc6 Nf3 Bg4 Be2 Qb6 dxc5 Qxc5 Be3 Qa5 O-O e6 Nbd2 Nge7 Nb3 Qc7 Bc5 Nf5 Bxf8 Kxf8 Re1 Bxf3 Bxf3 Nxe5 Be2 g6 Qd2 Kg7 g4 Ne7 Qg5 h6 Qf4 g5 Qg3 N7g6 Bf1 Nf4 Nd4 a6 Ne2 Neg6 Nd4 Nh4 Re3 e5 Nf5+ Nxf5 gxf5 f6 Qg4 h5 Qd1 h4", "perf": "blitz", "pgn": "[Event \"Rated blitz game\"]\n[Site \"https://lichess.org/D2HbJNUJ\"]\n[Date \"2021.07.04\"]\n[White \"Fediv_Alexandr\"]\n[Black \"Matei_Popescu1510\"]\n[Result \"0-1\"]\n[UTCDate \"2021.07.04\"]\n[UTCTime \"11:50:25\"]\n[WhiteElo \"1811\"]\n[BlackElo \"1832\"]\n[WhiteRatingDiff \"-11\"]\n[BlackRatingDiff \"+6\"]\n[Variant \"Standard\"]\n[TimeControl \"300+3\"]\n[ECO \"B12\"]\n[Termination \"Time forfeit\"]\n\n1. e4 c6 2. d4 d5 3. e5 c5 4. c3 Nc6 5. Nf3 Bg4 6. Be2 Qb6 7. dxc5 Qxc5 8. Be3 Qa5 9. O-O e6 10. Nbd2 Nge7 11. Nb3 Qc7 12. Bc5 Nf5 13. Bxf8 Kxf8 14. Re1 Bxf3 15. Bxf3 Nxe5 16. Be2 g6 17. Qd2 Kg7 18. g4 Ne7 19. Qg5 h6 20. Qf4 g5 21. Qg3 N7g6 22. Bf1 Nf4 23. Nd4 a6 24. Ne2 Neg6 25. Nd4 Nh4 26. Re3 e5 27. Nf5+ Nxf5 28. gxf5 f6 29. Qg4 h5 30. Qd1 h4 0-1\n\n\n", "players": {"black": {"rating": 1832, "ratingDiff": 6, "user": {"id": "matei_popescu1510", "name": "Matei_Popescu1510"}}, "white": {"rating": 1811, "ratingDiff": -11, "user": {"id": "fediv_alexandr", "name": "Fediv_Alexandr"}}}, "rated": true, "source": "pool", "speed": "blitz", "status": "timeout", "variant": "standard", "winner": "black"}