{"clock": {"increment": 3, "initial": 300, "totalTime": 420}, "createdAt": "2021-07-05 17:05:14.109000+00:00", "id": "dDQhMuxC", "lastMoveAt": "2021-07-05 17:10:44.748000+00:00", "moves": "d4 c6 Bf4 d5 e3 c5 Bb5+ Bd7 Bxd7+ Qxd7 Nf3 Nc6 c3 e6 O-O Nf6 Ne5 Nxe5 Bxe5 Bd6 Bxd6 Qxd6 Nd2 O-O Nf3 Ne4 Qc2 c4 b3 b5 bxc4 bxc4 Rac1 Rab8 Ne5 f6 Nxc4 dxc4 Qxe4 Rb2 Rc2 Rfb8 Rfc1 Kf7 Qxh7 Qa3 h3 Rxa2 e4 Rxc2 Rxc2 Qa1+ Kh2 Rb1 d5 Rh1+ Kg3 Qb1 Re2 Qb8+ f4 exd5 exd5 Rf1 Qh5+ Kg8 Re8+", "perf": "blitz", "pgn": "[Event \"Rated blitz game\"]\n[Site \"https://lichess.org/dDQhMuxC\"]\n[Date \"2021.07.05\"]\n[White \"JustKing97\"]\n[Black \"Matei_Popescu1510\"]\n[Result \"1-0\"]\n[UTCDate \"2021.07.05\"]\n[UTCTime \"17:05:14\"]\n[WhiteElo \"1784\"]\n[BlackElo \"1828\"]\n[WhiteRatingDiff \"+6\"]\n[BlackRatingDiff \"-7\"]\n[Variant \"Standard\"]\n[TimeControl \"300+3\"]\n[ECO \"A40\"]\n[Termination \"Normal\"]\n\n1. d4 c6 2. Bf4 d5 3. e3 c5 4. Bb5+ Bd7 5. Bxd7+ Qxd7 6. Nf3 Nc6 7. c3 e6 8. O-O Nf6 9. Ne5 Nxe5 10. Bxe5 Bd6 11. Bxd6 Qxd6 12. Nd2 O-O 13. Nf3 Ne4 14. Qc2 c4 15. b3 b5 16. bxc4 bxc4 17. Rac1 Rab8 18. Ne5 f6 19. Nxc4 dxc4 20. Qxe4 Rb2 21. Rc2 Rfb8 22. Rfc1 Kf7 23. Qxh7 Qa3 24. h3 Rxa2 25. e4 Rxc2 26. Rxc2 Qa1+ 27. Kh2 Rb1 28. d5 Rh1+ 29. Kg3 Qb1 30. Re2 Qb8+ 31. f4 exd5 32. exd5 Rf1 33. Qh5+ Kg8 34. Re8+ 1-0\n\n\n", "players": {"black": {"rating": 1828, "ratingDiff": -7, "user": {"id": "matei_popescu1510", "name": "Matei_Popescu1510"}}, "white": {"rating": 1784, "ratingDiff": 6, "user": {"id": "justking97", "name": "JustKing97"}}}, "rated": true, "source": "pool", "speed": "blitz", "status": "resign", "variant": "standard", "winner": "white"}