{"clock": {"increment": 3, "initial": 300, "totalTime": 420}, "createdAt": "2021-12-06 21:32:00.633000+00:00", "id": "DjPxUNb4", "lastMoveAt": "2021-12-06 21:37:31.551000+00:00", "moves": "c4 g6 Nc3 Bg7 e4 c5 Nf3 Nc6 g3 e6 Bg2 Nge7 O-O O-O Nb5 d5 exd5 exd5 d3 d4 Bf4 Be6 Re1 Bd7 Qd2 Rc8 h3 a6 Nd6 Rb8 Ng5 f6 Ne6 Bxe6 Rxe6 Nc8 Nxb7", "perf": "blitz", "pgn": "[Event \"Rated blitz game\"]\n[Site \"https://lichess.org/DjPxUNb4\"]\n[Date \"2021.12.06\"]\n[White \"MarkusErwin\"]\n[Black \"Matei_Popescu1510\"]\n[Result \"1-0\"]\n[UTCDate \"2021.12.06\"]\n[UTCTime \"21:32:00\"]\n[WhiteElo \"1926\"]\n[BlackElo \"1866\"]\n[WhiteRatingDiff \"+5\"]\n[BlackRatingDiff \"-5\"]\n[Variant \"Standard\"]\n[TimeControl \"300+3\"]\n[ECO \"A10\"]\n[Termination \"Time forfeit\"]\n\n1. c4 g6 2. Nc3 Bg7 3. e4 c5 4. Nf3 Nc6 5. g3 e6 6. Bg2 Nge7 7. O-O O-O 8. Nb5 d5 9. exd5 exd5 10. d3 d4 11. Bf4 Be6 12. Re1 Bd7 13. Qd2 Rc8 14. h3 a6 15. Nd6 Rb8 16. Ng5 f6 17. Ne6 Bxe6 18. Rxe6 Nc8 19. Nxb7 1-0\n\n\n", "players": {"black": {"rating": 1866, "ratingDiff": -5, "user": {"id": "matei_popescu1510", "name": "Matei_Popescu1510"}}, "white": {"rating": 1926, "ratingDiff": 5, "user": {"id": "markuserwin", "name": "MarkusErwin"}}}, "rated": true, "source": "pool", "speed": "blitz", "status": "timeout", "variant": "standard", "winner": "white"}