{"clock": {"increment": 3, "initial": 300, "totalTime": 420}, "createdAt": "2021-08-03 20:13:35.115000+00:00", "id": "dm2XNyYA", "lastMoveAt": "2021-08-03 20:21:21.976000+00:00", "moves": "e4 c6 Nf3 d5 exd5 cxd5 d4 Nc6 Be2 Bg4 O-O Nf6 c3 Qc7 h3 Bh5 Nh2 Bxe2 Qxe2 e6 Ng4 Ne4 Nd2 f5 Nxe4 fxe4 Ne3 Qf7 Qg4 Be7 Nd1 O-O Bg5 e5 Bxe7 Qxe7 dxe5 Nxe5 Qe2 Nd3 Ne3 Rad8 Rad1 Qc5 Rd2 Rd7 Qg4 Rdf7 Qe6 Nf4 Qe5 Qc8 Nxd5 Nxh3+ gxh3 Qxh3 Qxe4 Rf5 Ne7+ Kh8 Nxf5", "perf": "blitz", "pgn": "[Event \"Rated blitz game\"]\n[Site \"https://lichess.org/dm2XNyYA\"]\n[Date \"2021.08.03\"]\n[White \"ASD1343\"]\n[Black \"Matei_Popescu1510\"]\n[Result \"1-0\"]\n[UTCDate \"2021.08.03\"]\n[UTCTime \"20:13:35\"]\n[WhiteElo \"1812\"]\n[BlackElo \"1848\"]\n[WhiteRatingDiff \"+6\"]\n[BlackRatingDiff \"-7\"]\n[Variant \"Standard\"]\n[TimeControl \"300+3\"]\n[ECO \"B13\"]\n[Termination \"Normal\"]\n\n1. e4 c6 2. Nf3 d5 3. exd5 cxd5 4. d4 Nc6 5. Be2 Bg4 6. O-O Nf6 7. c3 Qc7 8. h3 Bh5 9. Nh2 Bxe2 10. Qxe2 e6 11. Ng4 Ne4 12. Nd2 f5 13. Nxe4 fxe4 14. Ne3 Qf7 15. Qg4 Be7 16. Nd1 O-O 17. Bg5 e5 18. Bxe7 Qxe7 19. dxe5 Nxe5 20. Qe2 Nd3 21. Ne3 Rad8 22. Rad1 Qc5 23. Rd2 Rd7 24. Qg4 Rdf7 25. Qe6 Nf4 26. Qe5 Qc8 27. Nxd5 Nxh3+ 28. gxh3 Qxh3 29. Qxe4 Rf5 30. Ne7+ Kh8 31. Nxf5 1-0\n\n\n", "players": {"black": {"rating": 1848, "ratingDiff": -7, "user": {"id": "matei_popescu1510", "name": "Matei_Popescu1510"}}, "white": {"rating": 1812, "ratingDiff": 6, "user": {"id": "asd1343", "name": "ASD1343"}}}, "rated": true, "source": "pool", "speed": "blitz", "status": "resign", "variant": "standard", "winner": "white"}