{"clock": {"increment": 2, "initial": 180, "totalTime": 260}, "createdAt": "2022-12-11 19:12:23.643000+00:00", "id": "dV0giPuu", "lastMoveAt": "2022-12-11 19:20:58.320000+00:00", "moves": "e4 c6 d3 d5 exd5 cxd5 Nf3 Bg4 Be2 Nf6 Nfd2 Bxe2 Qxe2 e6 O-O Bd6 Nf3 h6 c3 O-O Nbd2 Nbd7 Nb3 Rc8 Re1 a6 h3 b5 Bd2 Nb6 Rac1 Re8 Nfd4 Bf8 Qf3 Nfd7 Qg3 Kh8 Re2 e5 Nf5 Kh7 Rce1 g6 Ne3 Bg7 Qf3 Nf6 Ng4 Nxg4 Qxg4 f5 Qg3 e4 d4 Nc4 Bc1 b4 Nc5 Qd6 Bf4 Qc6 h4 bxc3 bxc3 Qb5 Bc1 Rb8 Qc7 Rec8 Qf7 Rxc5 dxc5 Qxc5 h5 gxh5 Qxf5+ Kh8 Qxh5 Rb1 Bxh6 Rxe1+ Rxe1 Kg8 Bxg7 Kxg7 Qg5+ Kh7 Qf5+ Kg7 Rxe4", "perf": "blitz", "pgn": "[Event \"Rated blitz game\"]\n[Site \"https://lichess.org/dV0giPuu\"]\n[Date \"2022.12.11\"]\n[White \"vvvad116\"]\n[Black \"Matei_Popescu1510\"]\n[Result \"1-0\"]\n[UTCDate \"2022.12.11\"]\n[UTCTime \"19:12:23\"]\n[WhiteElo \"1967\"]\n[BlackElo \"1912\"]\n[WhiteRatingDiff \"+5\"]\n[BlackRatingDiff \"-5\"]\n[Variant \"Standard\"]\n[TimeControl \"180+2\"]\n[ECO \"B10\"]\n[Termination \"Time forfeit\"]\n\n1. e4 c6 2. d3 d5 3. exd5 cxd5 4. Nf3 Bg4 5. Be2 Nf6 6. Nfd2 Bxe2 7. Qxe2 e6 8. O-O Bd6 9. Nf3 h6 10. c3 O-O 11. Nbd2 Nbd7 12. Nb3 Rc8 13. Re1 a6 14. h3 b5 15. Bd2 Nb6 16. Rac1 Re8 17. Nfd4 Bf8 18. Qf3 Nfd7 19. Qg3 Kh8 20. Re2 e5 21. Nf5 Kh7 22. Rce1 g6 23. Ne3 Bg7 24. Qf3 Nf6 25. Ng4 Nxg4 26. Qxg4 f5 27. Qg3 e4 28. d4 Nc4 29. Bc1 b4 30. Nc5 Qd6 31. Bf4 Qc6 32. h4 bxc3 33. bxc3 Qb5 34. Bc1 Rb8 35. Qc7 Rec8 36. Qf7 Rxc5 37. dxc5 Qxc5 38. h5 gxh5 39. Qxf5+ Kh8 40. Qxh5 Rb1 41. Bxh6 Rxe1+ 42. Rxe1 Kg8 43. Bxg7 Kxg7 44. Qg5+ Kh7 45. Qf5+ Kg7 46. Rxe4 1-0\n\n\n", "players": {"black": {"rating": 1912, "ratingDiff": -5, "user": {"id": "matei_popescu1510", "name": "Matei_Popescu1510"}}, "white": {"rating": 1967, "ratingDiff": 5, "user": {"id": "vvvad116", "name": "vvvad116"}}}, "rated": true, "source": "pool", "speed": "blitz", "status": "outoftime", "variant": "standard", "winner": "white"}