{"clock": {"increment": 1, "initial": 120, "totalTime": 160}, "createdAt": "2024-04-24 10:06:44.823000+00:00", "id": "gDcdncP7", "lastMoveAt": "2024-04-24 10:13:29.344000+00:00", "moves": "d4 Nf6 Nf3 g6 Bg5 Bg7 Bxf6 Bxf6 e4 d6 Nbd2 O-O h3 Nc6 c3 e5 Nb3 Bg7 d5 Ne7 Bd3 a5 O-O a4 Nbd2 f5 c4 b6 a3 f4 b3 axb3 Nxb3 h6 a4 g5 Qd2 Ng6 a5 bxa5 Rxa5 Rxa5 Qxa5 g4 hxg4 Bxg4 Be2 Qd7 c5 Bf6 c6 Qc8 Nbd2 Nh4 Qb5 Rf7 Rb1 Rg7 Qb7 Kh7 Qxc8 Bxc8 Nxh4 Bxh4 Nf3 Bf6 Rb8 Bh3 Bf1 Bg4 Nd2 Bd1 Nc4 Bc2 f3 Bb3 Na5 Bc2 Nb7 Rg8 Rxg8 Kxg8 Na5 Ba4 Kf2 Bd8 Ke2 Bb5+ Ke1 Bxf1 Kxf1 Kf7 Nc4 Ke8 Nd2 Bh4 Ke2 Bg3 Nf1 Kd8 Nxg3 fxg3 Kf1 h5 Ke2 h4 Kf1 Ke7 Ke2 Kf6 Kf1 Kg5 Kg1 Kf4 Kf1 Ke3 Kg1 Kf4 Kh1 h3 gxh3 Kxf3 Kg1 Kxe4 h4 Kf4 Kg2 Kg4 h5 Kxh5 Kxg3 Kg5 Kf3 Kf5 Ke3 Kg4 Ke4 Kg5 Ke3 Kf5 Kf3 e4+ Ke3 Ke5 Ke2 Kxd5 Ke3 Kxc6 Kxe4 Kc5 Kd3 d5 Kc3 c6 Kd3 d4 Ke4 Kc4 Ke5 d3", "perf": "bullet", "pgn": "[Event \"Rated bullet game\"]\n[Site \"https://lichess.org/gDcdncP7\"]\n[Date \"2024.04.24\"]\n[White \"joeben1\"]\n[Black \"Matei_Popescu1510\"]\n[Result \"0-1\"]\n[UTCDate \"2024.04.24\"]\n[UTCTime \"10:06:44\"]\n[WhiteElo \"1667\"]\n[BlackElo \"1766\"]\n[WhiteRatingDiff \"-4\"]\n[BlackRatingDiff \"+15\"]\n[Variant \"Standard\"]\n[TimeControl \"120+1\"]\n[ECO \"A48\"]\n[Termination \"Normal\"]\n\n1. d4 Nf6 2. Nf3 g6 3. Bg5 Bg7 4. Bxf6 Bxf6 5. e4 d6 6. Nbd2 O-O 7. h3 Nc6 8. c3 e5 9. Nb3 Bg7 10. d5 Ne7 11. Bd3 a5 12. O-O a4 13. Nbd2 f5 14. c4 b6 15. a3 f4 16. b3 axb3 17. Nxb3 h6 18. a4 g5 19. Qd2 Ng6 20. a5 bxa5 21. Rxa5 Rxa5 22. Qxa5 g4 23. hxg4 Bxg4 24. Be2 Qd7 25. c5 Bf6 26. c6 Qc8 27. Nbd2 Nh4 28. Qb5 Rf7 29. Rb1 Rg7 30. Qb7 Kh7 31. Qxc8 Bxc8 32. Nxh4 Bxh4 33. Nf3 Bf6 34. Rb8 Bh3 35. Bf1 Bg4 36. Nd2 Bd1 37. Nc4 Bc2 38. f3 Bb3 39. Na5 Bc2 40. Nb7 Rg8 41. Rxg8 Kxg8 42. Na5 Ba4 43. Kf2 Bd8 44. Ke2 Bb5+ 45. Ke1 Bxf1 46. Kxf1 Kf7 47. Nc4 Ke8 48. Nd2 Bh4 49. Ke2 Bg3 50. Nf1 Kd8 51. Nxg3 fxg3 52. Kf1 h5 53. Ke2 h4 54. Kf1 Ke7 55. Ke2 Kf6 56. Kf1 Kg5 57. Kg1 Kf4 58. Kf1 Ke3 59. Kg1 Kf4 60. Kh1 h3 61. gxh3 Kxf3 62. Kg1 Kxe4 63. h4 Kf4 64. Kg2 Kg4 65. h5 Kxh5 66. Kxg3 Kg5 67. Kf3 Kf5 68. Ke3 Kg4 69. Ke4 Kg5 70. Ke3 Kf5 71. Kf3 e4+ 72. Ke3 Ke5 73. Ke2 Kxd5 74. Ke3 Kxc6 75. Kxe4 Kc5 76. Kd3 d5 77. Kc3 c6 78. Kd3 d4 79. Ke4 Kc4 80. Ke5 d3 0-1\n\n\n", "players": {"black": {"rating": 1766, "ratingDiff": 15, "user": {"id": "matei_popescu1510", "name": "Matei_Popescu1510"}}, "white": {"rating": 1667, "ratingDiff": -4, "user": {"id": "joeben1", "name": "joeben1"}}}, "rated": true, "source": "pool", "speed": "bullet", "status": "resign", "variant": "standard", "winner": "black"}