{"clock": {"increment": 2, "initial": 180, "totalTime": 260}, "createdAt": "2022-07-25 11:19:52.169000+00:00", "id": "GxQ9IQqg", "lastMoveAt": "2022-07-25 11:27:38.892000+00:00", "moves": "e4 c6 d4 d5 e5 c5 c3 Nc6 Nf3 Bg4 Be2 e6 O-O cxd4 cxd4 Nge7 Nc3 Nf5 Be3 Be7 Bb5 a6 Bxc6+ bxc6 Bf4 O-O h3 Bxf3 gxf3 Bb4 Kh2 Bxc3 bxc3 c5 Rg1 cxd4 cxd4 Rb8 Qd3 Rb6 Rg5 Qd7 Rag1 Rfb8 Rh5 g6 Rhg5 h6 Rh5 Kh7 Rxf5 exf5 Bg3 Rb2 Qe3 Rxa2 Qf4 Rbb2 Bh4 Qb5 Bf6 Rxf2+ Kh1 Rh2+ Qxh2 Rxh2+ Kxh2 Qe2+ Kg3 Qd2 Rb1 Qxd4 Rb8 g5 Rh8+ Kg6 Rg8+ Kh5 h4 Qf4+ Kg2 Qxh4 Bxg5 Qxg5+ Rxg5+ hxg5 Kf2 a5 Ke3 Kh4 Kd4 Kg3 Kxd5 Kxf3 Kd6 g4 Ke7 g3 Kxf7 g2 e6 g1=Q e7 Qe1 e8=Q Qxe8+ Kxe8 a4", "perf": "blitz", "pgn": "[Event \"Rated blitz game\"]\n[Site \"https://lichess.org/GxQ9IQqg\"]\n[Date \"2022.07.25\"]\n[White \"Samhain338\"]\n[Black \"Matei_Popescu1510\"]\n[Result \"0-1\"]\n[UTCDate \"2022.07.25\"]\n[UTCTime \"11:19:52\"]\n[WhiteElo \"1826\"]\n[BlackElo \"1835\"]\n[WhiteRatingDiff \"-6\"]\n[BlackRatingDiff \"+6\"]\n[Variant \"Standard\"]\n[TimeControl \"180+2\"]\n[ECO \"B12\"]\n[Termination \"Normal\"]\n\n1. e4 c6 2. d4 d5 3. e5 c5 4. c3 Nc6 5. Nf3 Bg4 6. Be2 e6 7. O-O cxd4 8. cxd4 Nge7 9. Nc3 Nf5 10. Be3 Be7 11. Bb5 a6 12. Bxc6+ bxc6 13. Bf4 O-O 14. h3 Bxf3 15. gxf3 Bb4 16. Kh2 Bxc3 17. bxc3 c5 18. Rg1 cxd4 19. cxd4 Rb8 20. Qd3 Rb6 21. Rg5 Qd7 22. Rag1 Rfb8 23. Rh5 g6 24. Rhg5 h6 25. Rh5 Kh7 26. Rxf5 exf5 27. Bg3 Rb2 28. Qe3 Rxa2 29. Qf4 Rbb2 30. Bh4 Qb5 31. Bf6 Rxf2+ 32. Kh1 Rh2+ 33. Qxh2 Rxh2+ 34. Kxh2 Qe2+ 35. Kg3 Qd2 36. Rb1 Qxd4 37. Rb8 g5 38. Rh8+ Kg6 39. Rg8+ Kh5 40. h4 Qf4+ 41. Kg2 Qxh4 42. Bxg5 Qxg5+ 43. Rxg5+ hxg5 44. Kf2 a5 45. Ke3 Kh4 46. Kd4 Kg3 47. Kxd5 Kxf3 48. Kd6 g4 49. Ke7 g3 50. Kxf7 g2 51. e6 g1=Q 52. e7 Qe1 53. e8=Q Qxe8+ 54. Kxe8 a4 0-1\n\n\n", "players": {"black": {"rating": 1835, "ratingDiff": 6, "user": {"id": "matei_popescu1510", "name": "Matei_Popescu1510"}}, "white": {"rating": 1826, "ratingDiff": -6, "user": {"id": "samhain338", "name": "Samhain338"}}}, "rated": true, "source": "pool", "speed": "blitz", "status": "resign", "variant": "standard", "winner": "black"}