{"clock": {"increment": 1, "initial": 120, "totalTime": 160}, "createdAt": "2022-04-02 10:55:14.121000+00:00", "id": "lACoUHoZ", "lastMoveAt": "2022-04-02 11:00:07.996000+00:00", "moves": "d4 d5 e3 Nc6 c4 e6 Nc3 Nce7 Nf3 c6 Bd3 Ng6 O-O Bd6 Qc2 N8e7 c5 Bc7 e4 O-O e5 f6 exf6 Rxf6 Bg5 Rf7 Rae1 Qe8 Bxe7 Nxe7 Bxh7+ Kh8 Ne5 Rf6 Bd3 Rh6 f4 Qh5 h3 Nf5 Bxf5 exf5 Rf3 Bxe5 Rxe5 Bd7 Ne2 Qg5 Rg3 Qf6 Kf2 Re8 Ng1 b6 b4 Rxe5 dxe5 Qd8 Qe2 a5 a3 bxc5 bxc5 Qb8 Nf3 Qb5 Ng5 Qxc5+ Kf1 Qxa3 Nf7+ Kg8 Nxh6+ Kf8 Qh5 Qxg3 Qf7#", "perf": "bullet", "pgn": "[Event \"Rated bullet game\"]\n[Site \"https://lichess.org/lACoUHoZ\"]\n[Date \"2022.04.02\"]\n[White \"Matei_Popescu1510\"]\n[Black \"Ordsm\"]\n[Result \"1-0\"]\n[UTCDate \"2022.04.02\"]\n[UTCTime \"10:55:14\"]\n[WhiteElo \"1622\"]\n[BlackElo \"1619\"]\n[WhiteRatingDiff \"+6\"]\n[BlackRatingDiff \"-6\"]\n[Variant \"Standard\"]\n[TimeControl \"120+1\"]\n[ECO \"D00\"]\n[Termination \"Normal\"]\n\n1. d4 d5 2. e3 Nc6 3. c4 e6 4. Nc3 Nce7 5. Nf3 c6 6. Bd3 Ng6 7. O-O Bd6 8. Qc2 N8e7 9. c5 Bc7 10. e4 O-O 11. e5 f6 12. exf6 Rxf6 13. Bg5 Rf7 14. Rae1 Qe8 15. Bxe7 Nxe7 16. Bxh7+ Kh8 17. Ne5 Rf6 18. Bd3 Rh6 19. f4 Qh5 20. h3 Nf5 21. Bxf5 exf5 22. Rf3 Bxe5 23. Rxe5 Bd7 24. Ne2 Qg5 25. Rg3 Qf6 26. Kf2 Re8 27. Ng1 b6 28. b4 Rxe5 29. dxe5 Qd8 30. Qe2 a5 31. a3 bxc5 32. bxc5 Qb8 33. Nf3 Qb5 34. Ng5 Qxc5+ 35. Kf1 Qxa3 36. Nf7+ Kg8 37. Nxh6+ Kf8 38. Qh5 Qxg3 39. Qf7# 1-0\n\n\n", "players": {"black": {"rating": 1619, "ratingDiff": -6, "user": {"id": "ordsm", "name": "Ordsm"}}, "white": {"rating": 1622, "ratingDiff": 6, "user": {"id": "matei_popescu1510", "name": "Matei_Popescu1510"}}}, "rated": true, "source": "pool", "speed": "bullet", "status": "mate", "variant": "standard", "winner": "white"}