{"clock": {"increment": 2, "initial": 180, "totalTime": 260}, "createdAt": "2022-08-01 10:59:33.820000+00:00", "id": "MCFurS80", "lastMoveAt": "2022-08-01 11:05:58.201000+00:00", "moves": "d4 e6 e3 Nf6 Bd3 d5 Nd2 c5 c3 Nc6 f4 Bd6 Ngf3 h5 O-O h4 h3 Qb6 Ne5 cxd4 cxd4 Nxd4 exd4 Qxd4+ Kh1 Bxe5 Bb5+ Bd7 Bxd7+ Nxd7 fxe5 Nxe5 Nf3 Nxf3 Qxf3 f5 Qf4 O-O-O Be3 Qxb2 Rfc1+ Kd7 Rc7+ Ke8 Rac1 Qxa2 Qg5 Rd7 Rxd7 Kxd7 Qxg7+", "perf": "blitz", "pgn": "[Event \"Rated blitz game\"]\n[Site \"https://lichess.org/MCFurS80\"]\n[Date \"2022.08.01\"]\n[White \"Matei_Popescu1510\"]\n[Black \"aksin420\"]\n[Result \"1-0\"]\n[UTCDate \"2022.08.01\"]\n[UTCTime \"10:59:33\"]\n[WhiteElo \"1849\"]\n[BlackElo \"1871\"]\n[WhiteRatingDiff \"+6\"]\n[BlackRatingDiff \"-6\"]\n[Variant \"Standard\"]\n[TimeControl \"180+2\"]\n[ECO \"A40\"]\n[Termination \"Time forfeit\"]\n\n1. d4 e6 2. e3 Nf6 3. Bd3 d5 4. Nd2 c5 5. c3 Nc6 6. f4 Bd6 7. Ngf3 h5 8. O-O h4 9. h3 Qb6 10. Ne5 cxd4 11. cxd4 Nxd4 12. exd4 Qxd4+ 13. Kh1 Bxe5 14. Bb5+ Bd7 15. Bxd7+ Nxd7 16. fxe5 Nxe5 17. Nf3 Nxf3 18. Qxf3 f5 19. Qf4 O-O-O 20. Be3 Qxb2 21. Rfc1+ Kd7 22. Rc7+ Ke8 23. Rac1 Qxa2 24. Qg5 Rd7 25. Rxd7 Kxd7 26. Qxg7+ 1-0\n\n\n", "players": {"black": {"rating": 1871, "ratingDiff": -6, "user": {"id": "aksin420", "name": "aksin420"}}, "white": {"rating": 1849, "ratingDiff": 6, "user": {"id": "matei_popescu1510", "name": "Matei_Popescu1510"}}}, "rated": true, "source": "pool", "speed": "blitz", "status": "outoftime", "variant": "standard", "winner": "white"}