{"clock": {"increment": 2, "initial": 180, "totalTime": 260}, "createdAt": "2022-09-01 10:37:54.906000+00:00", "id": "s8ZLYmdM", "lastMoveAt": "2022-09-01 10:47:19.186000+00:00", "moves": "d4 Nf6 Bg5 g6 e3 Bg7 Bd3 O-O Nd2 d6 c3 c5 f4 Nc6 Ngf3 Ne8 O-O f5 Qe1 Nf6 Qh4 Nh5 Qf2 a6 a4 b6 Ne1 Bb7 Be2 Nf6 Qh4 Qd7 Rf3 e5 Rh3 h5 Bd3 exd4 exd4 cxd4 c4 Nb4 Bb1 Rae8 Nd3 Nxd3 Bxd3 Re3 Re1 Rfe8 Rexe3 Rxe3 Bxf6 Rxh3 gxh3 Qc6 Kf2 Qg2+ Ke1 Qh1+ Ke2 Qg2+ Kd1 Qg1+ Kc2 Be4 Bxe4 fxe4 Bxg7 d3+ Kb3 Qd1+ Ka2 Qxa4+ Kb1 Qc2+ Ka1 Kxg7 Qe7+ Kh6 Qg5+ Kg7 Qe7+ Kg8 Qe6+ Kf8 Qxd6+ Kf7 Qd5+ Ke8 Qxe4+ Kd8 Qd4+ Kc8 Qh8+ Kc7 Qg7+ Kc6 Qxg6+ Kc5 Qf5+ Kb4 Qf8+ Ka5 Qa3+ Qa4 Qxa4+ Kxa4 Kb1", "perf": "blitz", "pgn": "[Event \"Rated blitz game\"]\n[Site \"https://lichess.org/s8ZLYmdM\"]\n[Date \"2022.09.01\"]\n[White \"Matei_Popescu1510\"]\n[Black \"Nettleson\"]\n[Result \"1-0\"]\n[UTCDate \"2022.09.01\"]\n[UTCTime \"10:37:54\"]\n[WhiteElo \"1938\"]\n[BlackElo \"1880\"]\n[WhiteRatingDiff \"+4\"]\n[BlackRatingDiff \"-5\"]\n[Variant \"Standard\"]\n[TimeControl \"180+2\"]\n[ECO \"A45\"]\n[Termination \"Normal\"]\n\n1. d4 Nf6 2. Bg5 g6 3. e3 Bg7 4. Bd3 O-O 5. Nd2 d6 6. c3 c5 7. f4 Nc6 8. Ngf3 Ne8 9. O-O f5 10. Qe1 Nf6 11. Qh4 Nh5 12. Qf2 a6 13. a4 b6 14. Ne1 Bb7 15. Be2 Nf6 16. Qh4 Qd7 17. Rf3 e5 18. Rh3 h5 19. Bd3 exd4 20. exd4 cxd4 21. c4 Nb4 22. Bb1 Rae8 23. Nd3 Nxd3 24. Bxd3 Re3 25. Re1 Rfe8 26. Rexe3 Rxe3 27. Bxf6 Rxh3 28. gxh3 Qc6 29. Kf2 Qg2+ 30. Ke1 Qh1+ 31. Ke2 Qg2+ 32. Kd1 Qg1+ 33. Kc2 Be4 34. Bxe4 fxe4 35. Bxg7 d3+ 36. Kb3 Qd1+ 37. Ka2 Qxa4+ 38. Kb1 Qc2+ 39. Ka1 Kxg7 40. Qe7+ Kh6 41. Qg5+ Kg7 42. Qe7+ Kg8 43. Qe6+ Kf8 44. Qxd6+ Kf7 45. Qd5+ Ke8 46. Qxe4+ Kd8 47. Qd4+ Kc8 48. Qh8+ Kc7 49. Qg7+ Kc6 50. Qxg6+ Kc5 51. Qf5+ Kb4 52. Qf8+ Ka5 53. Qa3+ Qa4 54. Qxa4+ Kxa4 55. Kb1 1-0\n\n\n", "players": {"black": {"rating": 1880, "ratingDiff": -5, "user": {"id": "nettleson", "name": "Nettleson"}}, "white": {"rating": 1938, "ratingDiff": 4, "user": {"id": "matei_popescu1510", "name": "Matei_Popescu1510"}}}, "rated": true, "source": "pool", "speed": "blitz", "status": "resign", "variant": "standard", "winner": "white"}