{"clock": {"increment": 2, "initial": 180, "totalTime": 260}, "createdAt": "2023-04-04 14:20:53.140000+00:00", "id": "uqfMQlP1", "lastMoveAt": "2023-04-04 14:24:18.428000+00:00", "moves": "d4 Nf6 Bg5 e6 e3 d5 Bd3 Be7 Nd2 b6 c3 a5 Qa4+ Qd7 Qxd7+ Bxd7 Bxf6 Bxf6 a4 c5 f4 c4 Bc2 O-O Ngf3 Nc6 O-O h6 Ne5 Nxe5 fxe5 Be7 e4 f6 exf6 Rxf6 e5 Rxf1+ Rxf1 Rf8 Rxf8+ Kxf8 Kf2 Bg5 Ke2 Be8 g3 Bh5+ Ke1 Be3 h3 g5 g4 Bg6 Bxg6", "perf": "blitz", "pgn": "[Event \"Rated blitz game\"]\n[Site \"https://lichess.org/uqfMQlP1\"]\n[Date \"2023.04.04\"]\n[White \"Matei_Popescu1510\"]\n[Black \"Wolfi71\"]\n[Result \"1-0\"]\n[UTCDate \"2023.04.04\"]\n[UTCTime \"14:20:53\"]\n[WhiteElo \"1876\"]\n[BlackElo \"1878\"]\n[WhiteRatingDiff \"+5\"]\n[BlackRatingDiff \"-6\"]\n[Variant \"Standard\"]\n[TimeControl \"180+2\"]\n[ECO \"A45\"]\n[Termination \"Normal\"]\n\n1. d4 Nf6 2. Bg5 e6 3. e3 d5 4. Bd3 Be7 5. Nd2 b6 6. c3 a5 7. Qa4+ Qd7 8. Qxd7+ Bxd7 9. Bxf6 Bxf6 10. a4 c5 11. f4 c4 12. Bc2 O-O 13. Ngf3 Nc6 14. O-O h6 15. Ne5 Nxe5 16. fxe5 Be7 17. e4 f6 18. exf6 Rxf6 19. e5 Rxf1+ 20. Rxf1 Rf8 21. Rxf8+ Kxf8 22. Kf2 Bg5 23. Ke2 Be8 24. g3 Bh5+ 25. Ke1 Be3 26. h3 g5 27. g4 Bg6 28. Bxg6 1-0\n\n\n", "players": {"black": {"rating": 1878, "ratingDiff": -6, "user": {"id": "wolfi71", "name": "Wolfi71"}}, "white": {"rating": 1876, "ratingDiff": 5, "user": {"id": "matei_popescu1510", "name": "Matei_Popescu1510"}}}, "rated": true, "source": "pool", "speed": "blitz", "status": "resign", "variant": "standard", "winner": "white"}