{"clock": {"increment": 2, "initial": 180, "totalTime": 260}, "createdAt": "2023-09-29 20:16:12.563000+00:00", "id": "v9itVQuR", "lastMoveAt": "2023-09-29 20:19:32.735000+00:00", "moves": "d4 Nf6 Bg5 Nd5 e4 Nb6 Bd3 g6 c3 Bg7 Qd2 O-O Bh6 d6 Bxg7 Kxg7 f4 N8d7 e5 dxe5 fxe5 c5 Nf3 c4 Bc2 Nd5 O-O N7b6 a4 a5 Ng5 h6 Ne4 Bf5 Nc5 Bxc2 Qxc2 e6 Qf2 Qe7 Nd2 Qg5 Rae1 Ne3 Qxe3 Qxe3+ Rxe3", "perf": "blitz", "pgn": "[Event \"Rated blitz game\"]\n[Site \"https://lichess.org/v9itVQuR\"]\n[Date \"2023.09.29\"]\n[White \"Matei_Popescu1510\"]\n[Black \"suckdustnbustnuts\"]\n[Result \"1-0\"]\n[UTCDate \"2023.09.29\"]\n[UTCTime \"20:16:12\"]\n[WhiteElo \"1915\"]\n[BlackElo \"1892\"]\n[WhiteRatingDiff \"+5\"]\n[BlackRatingDiff \"-5\"]\n[Variant \"Standard\"]\n[TimeControl \"180+2\"]\n[ECO \"A45\"]\n[Termination \"Normal\"]\n\n1. d4 Nf6 2. Bg5 Nd5 3. e4 Nb6 4. Bd3 g6 5. c3 Bg7 6. Qd2 O-O 7. Bh6 d6 8. Bxg7 Kxg7 9. f4 N8d7 10. e5 dxe5 11. fxe5 c5 12. Nf3 c4 13. Bc2 Nd5 14. O-O N7b6 15. a4 a5 16. Ng5 h6 17. Ne4 Bf5 18. Nc5 Bxc2 19. Qxc2 e6 20. Qf2 Qe7 21. Nd2 Qg5 22. Rae1 Ne3 23. Qxe3 Qxe3+ 24. Rxe3 1-0\n\n\n", "players": {"black": {"rating": 1892, "ratingDiff": -5, "user": {"id": "suckdustnbustnuts", "name": "suckdustnbustnuts"}}, "white": {"rating": 1915, "ratingDiff": 5, "user": {"id": "matei_popescu1510", "name": "Matei_Popescu1510"}}}, "rated": true, "source": "pool", "speed": "blitz", "status": "resign", "variant": "standard", "winner": "white"}