{"clock": {"increment": 1, "initial": 120, "totalTime": 160}, "createdAt": "2021-01-15 20:28:33.435000+00:00", "id": "X3xL0s8U", "lastMoveAt": "2021-01-15 20:31:31.988000+00:00", "moves": "e4 c5 Nc3 g6 f4 Bg7 Nf3 Nc6 Bb5 d6 d3 e6 Rb1 Ne7 a3 a6 Bc4 b5 Ba2 O-O O-O d5 e5 d4 Ne2 Nd5 Ng5 h6 Ne4 Nce7 Nd6 Qc7 g4 Bb7 Ng3 Nb6 Nge4 Bxe4 Nxe4 Nbd5 Nd6 Nc8 Ne4 Ncb6 Qf3 Rad8 Nd6 Nc8 Ne4 Ncb6 Nd6 Nc8 Ne4 Ncb6", "perf": "bullet", "pgn": "[Event \"Rated bullet game\"]\n[Site \"https://lichess.org/X3xL0s8U\"]\n[Date \"2021.01.15\"]\n[White \"Lgi21\"]\n[Black \"Matei_Popescu1510\"]\n[Result \"1/2-1/2\"]\n[UTCDate \"2021.01.15\"]\n[UTCTime \"20:28:33\"]\n[WhiteElo \"1587\"]\n[BlackElo \"1591\"]\n[WhiteRatingDiff \"+1\"]\n[BlackRatingDiff \"+0\"]\n[Variant \"Standard\"]\n[TimeControl \"120+1\"]\n[ECO \"B23\"]\n[Termination \"Normal\"]\n\n1. e4 c5 2. Nc3 g6 3. f4 Bg7 4. Nf3 Nc6 5. Bb5 d6 6. d3 e6 7. Rb1 Ne7 8. a3 a6 9. Bc4 b5 10. Ba2 O-O 11. O-O d5 12. e5 d4 13. Ne2 Nd5 14. Ng5 h6 15. Ne4 Nce7 16. Nd6 Qc7 17. g4 Bb7 18. Ng3 Nb6 19. Nge4 Bxe4 20. Nxe4 Nbd5 21. Nd6 Nc8 22. Ne4 Ncb6 23. Qf3 Rad8 24. Nd6 Nc8 25. Ne4 Ncb6 26. Nd6 Nc8 27. Ne4 Ncb6 1/2-1/2\n\n\n", "players": {"black": {"rating": 1591, "ratingDiff": 0, "user": {"id": "matei_popescu1510", "name": "Matei_Popescu1510"}}, "white": {"rating": 1587, "ratingDiff": 1, "user": {"id": "lgi21", "name": "Lgi21"}}}, "rated": true, "source": "pool", "speed": "bullet", "status": "draw", "variant": "standard"}