{"clock": {"increment": 2, "initial": 180, "totalTime": 260}, "createdAt": "2023-01-30 11:55:33.902000+00:00", "id": "xVJImhmh", "lastMoveAt": "2023-01-30 12:02:54.300000+00:00", "moves": "e4 c6 d4 d5 Nc3 dxe4 Nxe4 Nf6 Ng3 Bg4 Nf3 e6 Be2 Bd6 Bg5 h6 Be3 O-O O-O Nbd7 c4 Re8 h3 Bxf3 Bxf3 Bf8 Qd2 Nb6 b3 Qe7 a4 a5 Rad1 Qc7 Bf4 Qe7 Rfe1 Red8 Re5 Qb4 Qd3 Nfd7 Rh5 Nf6 Rh4 g5 Bxg5 hxg5 Nh5 Qe7 Nxf6+ Qxf6 Qh7#", "perf": "blitz", "pgn": "[Event \"Rated blitz game\"]\n[Site \"https://lichess.org/xVJImhmh\"]\n[Date \"2023.01.30\"]\n[White \"frocodillo\"]\n[Black \"Matei_Popescu1510\"]\n[Result \"1-0\"]\n[UTCDate \"2023.01.30\"]\n[UTCTime \"11:55:33\"]\n[WhiteElo \"1880\"]\n[BlackElo \"1878\"]\n[WhiteRatingDiff \"+5\"]\n[BlackRatingDiff \"-5\"]\n[Variant \"Standard\"]\n[TimeControl \"180+2\"]\n[ECO \"B15\"]\n[Termination \"Normal\"]\n\n1. e4 c6 2. d4 d5 3. Nc3 dxe4 4. Nxe4 Nf6 5. Ng3 Bg4 6. Nf3 e6 7. Be2 Bd6 8. Bg5 h6 9. Be3 O-O 10. O-O Nbd7 11. c4 Re8 12. h3 Bxf3 13. Bxf3 Bf8 14. Qd2 Nb6 15. b3 Qe7 16. a4 a5 17. Rad1 Qc7 18. Bf4 Qe7 19. Rfe1 Red8 20. Re5 Qb4 21. Qd3 Nfd7 22. Rh5 Nf6 23. Rh4 g5 24. Bxg5 hxg5 25. Nh5 Qe7 26. Nxf6+ Qxf6 27. Qh7# 1-0\n\n\n", "players": {"black": {"rating": 1878, "ratingDiff": -5, "user": {"id": "matei_popescu1510", "name": "Matei_Popescu1510"}}, "white": {"rating": 1880, "ratingDiff": 5, "user": {"id": "frocodillo", "name": "frocodillo"}}}, "rated": true, "source": "pool", "speed": "blitz", "status": "mate", "variant": "standard", "winner": "white"}