{"clock": {"increment": 1, "initial": 120, "totalTime": 160}, "createdAt": "2024-04-22 16:11:41.759000+00:00", "id": "ZK8eDPt2", "lastMoveAt": "2024-04-22 16:13:34.550000+00:00", "moves": "e4 c6 Bc4 d5 exd5 cxd5 Bb3 a5 a4 Nc6 d4 Nf6 Nf3 Bg4 Bf4 e6 Nbd2 Nxd4 O-O Nxb3 cxb3 Bd6 Bg5 Be7 Qe1 Bxf3 Nxf3 O-O Rd1 Rc8 Ne5 Qc7 Bh4 Ne4 Bxe7 Qxe7 f3 Qc5+ Kh1 Nd6 Nd7 Qb6", "perf": "bullet", "pgn": "[Event \"Rated bullet game\"]\n[Site \"https://lichess.org/ZK8eDPt2\"]\n[Date \"2024.04.22\"]\n[White \"greentea7\"]\n[Black \"Matei_Popescu1510\"]\n[Result \"1-0\"]\n[UTCDate \"2024.04.22\"]\n[UTCTime \"16:11:41\"]\n[WhiteElo \"1801\"]\n[BlackElo \"1805\"]\n[WhiteRatingDiff \"+5\"]\n[BlackRatingDiff \"-33\"]\n[Variant \"Standard\"]\n[TimeControl \"120+1\"]\n[ECO \"B10\"]\n[Termination \"Normal\"]\n\n1. e4 c6 2. Bc4 d5 3. exd5 cxd5 4. Bb3 a5 5. a4 Nc6 6. d4 Nf6 7. Nf3 Bg4 8. Bf4 e6 9. Nbd2 Nxd4 10. O-O Nxb3 11. cxb3 Bd6 12. Bg5 Be7 13. Qe1 Bxf3 14. Nxf3 O-O 15. Rd1 Rc8 16. Ne5 Qc7 17. Bh4 Ne4 18. Bxe7 Qxe7 19. f3 Qc5+ 20. Kh1 Nd6 21. Nd7 Qb6 1-0\n\n\n", "players": {"black": {"provisional": true, "rating": 1805, "ratingDiff": -33, "user": {"id": "matei_popescu1510", "name": "Matei_Popescu1510"}}, "white": {"rating": 1801, "ratingDiff": 5, "user": {"id": "greentea7", "name": "greentea7"}}}, "rated": true, "source": "pool", "speed": "bullet", "status": "resign", "variant": "standard", "winner": "white"}