{"clock": {"increment": 2, "initial": 180, "totalTime": 260}, "createdAt": "2022-06-29 09:05:38.738000+00:00", "id": "ZWX0zeA1", "lastMoveAt": "2022-06-29 09:15:27.698000+00:00", "moves": "d4 e6 c3 d5 Bf4 c5 e3 Nc6 Nd2 Qb6 Qc2 Nf6 dxc5 Bxc5 Bd3 Bd7 Ne2 Rc8 a3 Be7 f3 e5 Bg5 h6 Bxf6 Bxf6 Nf1 O-O Neg3 Bh4 Qe2 Rce8 Bc2 d4 Qd3 g6 O-O-O Bf6 exd4 exd4 Ne4 Bg7 c4 Bf5 g4 Bxe4 fxe4 Ne5 Qe2 Rd8 Bd3 Qc7 Nd2 a6 h4 b5 Kb1 bxc4 Nxc4 Nxd3 Qxd3 Rc8 Rc1 Qe7 h5 g5 Rhe1 Rc7 e5 Rfc8 Ka1 Qe6 b3 Bxe5 Rxe5 Qxe5 Nxe5 Rxc1+ Kb2 R1c7 a4 a5 Nc4 Rd8 Nxa5 Rc3 Qd2 Rf3 Nc4 d3 Ka3 Rf4 Ne5 Re4 Nf3 Re2 Qd1 Re3 Ng1 Rg3 a5 d2 a6 Rxg1 Qxg1 d1=Q Qxd1 Rxd1 b4 Rd8 b5 Ra8 Kb4 Kf8 Kc5 Ke7 Kc6 Kd8 Kb7 Rc8 a7 Rc7+ Kb6 Rc8 Ka6 Ra8 b6 Kc8 b7+", "perf": "blitz", "pgn": "[Event \"Rated blitz game\"]\n[Site \"https://lichess.org/ZWX0zeA1\"]\n[Date \"2022.06.29\"]\n[White \"Ayman-ALKING1\"]\n[Black \"Matei_Popescu1510\"]\n[Result \"1-0\"]\n[UTCDate \"2022.06.29\"]\n[UTCTime \"09:05:38\"]\n[WhiteElo \"2063\"]\n[BlackElo \"1981\"]\n[WhiteRatingDiff \"+5\"]\n[BlackRatingDiff \"-5\"]\n[Variant \"Standard\"]\n[TimeControl \"180+2\"]\n[ECO \"A40\"]\n[Termination \"Normal\"]\n\n1. d4 e6 2. c3 d5 3. Bf4 c5 4. e3 Nc6 5. Nd2 Qb6 6. Qc2 Nf6 7. dxc5 Bxc5 8. Bd3 Bd7 9. Ne2 Rc8 10. a3 Be7 11. f3 e5 12. Bg5 h6 13. Bxf6 Bxf6 14. Nf1 O-O 15. Neg3 Bh4 16. Qe2 Rce8 17. Bc2 d4 18. Qd3 g6 19. O-O-O Bf6 20. exd4 exd4 21. Ne4 Bg7 22. c4 Bf5 23. g4 Bxe4 24. fxe4 Ne5 25. Qe2 Rd8 26. Bd3 Qc7 27. Nd2 a6 28. h4 b5 29. Kb1 bxc4 30. Nxc4 Nxd3 31. Qxd3 Rc8 32. Rc1 Qe7 33. h5 g5 34. Rhe1 Rc7 35. e5 Rfc8 36. Ka1 Qe6 37. b3 Bxe5 38. Rxe5 Qxe5 39. Nxe5 Rxc1+ 40. Kb2 R1c7 41. a4 a5 42. Nc4 Rd8 43. Nxa5 Rc3 44. Qd2 Rf3 45. Nc4 d3 46. Ka3 Rf4 47. Ne5 Re4 48. Nf3 Re2 49. Qd1 Re3 50. Ng1 Rg3 51. a5 d2 52. a6 Rxg1 53. Qxg1 d1=Q 54. Qxd1 Rxd1 55. b4 Rd8 56. b5 Ra8 57. Kb4 Kf8 58. Kc5 Ke7 59. Kc6 Kd8 60. Kb7 Rc8 61. a7 Rc7+ 62. Kb6 Rc8 63. Ka6 Ra8 64. b6 Kc8 65. b7+ 1-0\n\n\n", "players": {"black": {"rating": 1981, "ratingDiff": -5, "user": {"id": "matei_popescu1510", "name": "Matei_Popescu1510"}}, "white": {"rating": 2063, "ratingDiff": 5, "user": {"id": "ayman-alking1", "name": "Ayman-ALKING1"}}}, "rated": true, "source": "pool", "speed": "blitz", "status": "resign", "variant": "standard", "winner": "white"}